pymarko/__init__.py
pymarko/ip.py
pymarko/mcsocket.py
pymarko/transport.py
pymarko/udpsocket.py
pymarko-0.5.0.dist-info/LICENSE
pymarko-0.5.0.dist-info/WHEEL
pymarko-0.5.0.dist-info/METADATA
pymarko-0.5.0.dist-info/RECORD
